mgz2imagetree
