Metadata-Version: 1.0
Name: mgz2imagetree
Version: 1.1.6
Summary: (Python) utility to filter mgz volumes to per-voxel-value directories of jpg/png image slices
Home-page: https://github.com/FNNDSC/mgz2imagetree
Author: FNNDSC
Author-email: dev@babymri.org
License: MIT
Platform: UNKNOWN
